birdeye/__init__.py
birdeye/_nodes.py
birdeye/birdeye.py
birdeye/cli.py
birdeye/file_tree_viewer.py
birdeye/file_tree_viewer.py.save
birdeye-0.3.0.dist-info/METADATA
birdeye-0.3.0.dist-info/WHEEL
birdeye-0.3.0.dist-info/entry_points.txt
birdeye-0.3.0.dist-info/RECORD
