Metadata-Version: 2.4
Name: birdeye
Version: 0.3.0
Summary: Add your description here
Author-email: Sander Teunissen <s.teunissen@gmail.com>
Requires-Python: >=3.13
Requires-Dist: prompt-toolkit>=3.0.51
Requires-Dist: pygit2>=1.19.0
